eazyml_cf/__init__.py
eazyml_cf/Darwin_arm64/__init__.py
eazyml_cf/Darwin_arm64/eazyml_cf/__init__.cpython-310-darwin.so
eazyml_cf/Darwin_arm64/eazyml_cf/__init__.cpython-311-darwin.so
eazyml_cf/Darwin_arm64/eazyml_cf/__init__.cpython-312-darwin.so
eazyml_cf/Darwin_arm64/eazyml_cf/__init__.cpython-38-darwin.so
eazyml_cf/Darwin_arm64/eazyml_cf/__init__.cpython-39-darwin.so
eazyml_cf/Darwin_arm64/eazyml_cf/client.cpython-310-darwin.so
eazyml_cf/Darwin_arm64/eazyml_cf/client.cpython-311-darwin.so
eazyml_cf/Darwin_arm64/eazyml_cf/client.cpython-312-darwin.so
eazyml_cf/Darwin_arm64/eazyml_cf/client.cpython-38-darwin.so
eazyml_cf/Darwin_arm64/eazyml_cf/client.cpython-39-darwin.so
eazyml_cf/Darwin_arm64/eazyml_cf/globals/__init__.cpython-310-darwin.so
eazyml_cf/Darwin_arm64/eazyml_cf/globals/__init__.cpython-311-darwin.so
eazyml_cf/Darwin_arm64/eazyml_cf/globals/__init__.cpython-312-darwin.so
eazyml_cf/Darwin_arm64/eazyml_cf/globals/__init__.cpython-38-darwin.so
eazyml_cf/Darwin_arm64/eazyml_cf/globals/__init__.cpython-39-darwin.so
eazyml_cf/Darwin_arm64/eazyml_cf/globals/config.cpython-310-darwin.so
eazyml_cf/Darwin_arm64/eazyml_cf/globals/config.cpython-311-darwin.so
eazyml_cf/Darwin_arm64/eazyml_cf/globals/config.cpython-312-darwin.so
eazyml_cf/Darwin_arm64/eazyml_cf/globals/config.cpython-38-darwin.so
eazyml_cf/Darwin_arm64/eazyml_cf/globals/config.cpython-39-darwin.so
eazyml_cf/Darwin_arm64/eazyml_cf/globals/license_vars.cpython-310-darwin.so
eazyml_cf/Darwin_arm64/eazyml_cf/globals/license_vars.cpython-311-darwin.so
eazyml_cf/Darwin_arm64/eazyml_cf/globals/license_vars.cpython-312-darwin.so
eazyml_cf/Darwin_arm64/eazyml_cf/globals/license_vars.cpython-38-darwin.so
eazyml_cf/Darwin_arm64/eazyml_cf/globals/license_vars.cpython-39-darwin.so
eazyml_cf/Darwin_arm64/eazyml_cf/globals/logger.cpython-310-darwin.so
eazyml_cf/Darwin_arm64/eazyml_cf/globals/logger.cpython-311-darwin.so
eazyml_cf/Darwin_arm64/eazyml_cf/globals/logger.cpython-312-darwin.so
eazyml_cf-0.0.45.dist-info/LICENSE
eazyml_cf-0.0.45.dist-info/METADATA
eazyml_cf-0.0.45.dist-info/WHEEL
eazyml_cf-0.0.45.dist-info/top_level.txt
eazyml_cf-0.0.45.dist-info/RECORD
