Metadata-Version: 2.1
Name: eazyml-cf
Version: 0.0.45
Summary: eazyml-cf provides APIs for counterfactual explanations, prescriptive analytics, and actionable insights to optimize predictive outcomes.
Home-page: https://eazyml.com/
Author: Eazyml
Author-email: admin@ipsoftlabs.com
Project-URL: Documentation, https://docs.eazyml.com/
Project-URL: Homepage, https://eazyml.com/
Project-URL: Contact Us, https://eazyml.com/trust-in-ai
Project-URL: eazyml, https://pypi.org/project/eazyml/
Project-URL: eazyml-cf, https://pypi.org/project/eazyml-cf/
Project-URL: eazyml-xai, https://pypi.org/project/eazyml-xai/
Project-URL: eazyml-xai-image, https://pypi.org/project/eazyml-xai-image/
Project-URL: eazyml-augi, https://pypi.org/project/eazyml-augi/
Project-URL: eazyml-dq, https://pypi.org/project/eazyml-dq/
Keywords: counterfactuals,prescriptive-analytics,optimal-decision,what-if-analysis,actionable-insights,prediction-optimization,causal-inference,machine-learning,ml-api,explainable-ai
Classifier: Development Status :: 5 - Production/Stable
Classifier: License :: Other/Proprietary License
Classifier: Intended Audience :: Developers
Classifier: Intended Audience :: Science/Research
Classifier: Intended Audience :: Information Technology
Classifier: Programming Language :: Python :: 3.8
Classifier: Programming Language :: Python :: 3.9
Classifier: Programming Language :: Python :: 3.10
Classifier: Programming Language :: Python :: 3.11
Classifier: Programming Language :: Python :: 3.12
Classifier: Topic :: Scientific/Engineering :: Artificial Intelligence
Classifier: Operating System :: Unix
Classifier: Operating System :: Microsoft :: Windows
Requires-Python: >=3.7
License-File: LICENSE
Requires-Dist: pandas
Requires-Dist: matplotlib
Requires-Dist: openpyxl
Requires-Dist: scikit-learn
Requires-Dist: scipy
Requires-Dist: getmac
Requires-Dist: cryptography
Requires-Dist: pyyaml
Requires-Dist: eazyml
